tmd_top/__init__.py
tmd_top/main.py
tmd_top/data/GeoLite2-City.mmdb
tmd_top/data/tmd-top.db
tmd_top-2.2.0.dist-info/LICENSE
tmd_top-2.2.0.dist-info/METADATA
tmd_top-2.2.0.dist-info/WHEEL
tmd_top-2.2.0.dist-info/entry_points.txt
tmd_top-2.2.0.dist-info/top_level.txt
tmd_top-2.2.0.dist-info/RECORD
