Metadata-Version: 2.1
Name: tmd-top
Version: 2.2.0
Summary: linux服务器网络流量分析工具，详细到ip连接情况
Home-page: https://gitee.com/Davin168/tmd-top
Author: Davin
Author-email: 949178863@qq.com
Classifier: Programming Language :: Python :: 3
Classifier: License :: OSI Approved :: MIT License
Classifier: Operating System :: OS Independent
Requires-Python: >=3.8
License-File: LICENSE
Requires-Dist: textual==1.0.0
Requires-Dist: typing_extensions==4.9.0
Requires-Dist: rich==13.7.1
Requires-Dist: geoip2==4.8.0
